urltrim/__init__.py
urltrim/core.py
urltrim-0.1.4.dist-info/LICENSE
urltrim-0.1.4.dist-info/METADATA
urltrim-0.1.4.dist-info/WHEEL
urltrim-0.1.4.dist-info/top_level.txt
urltrim-0.1.4.dist-info/RECORD
