Metadata-Version: 2.1
Name: urltrim
Version: 0.1.4
Summary: A Python library to trim long URLs in code
Home-page: https://github.com/upraneethkumar/urltrim
Author: PRANEETH KUMAR UDDARAJU
Author-email: PRANEETH KUMAR UDDARAJU <upraneeth24@gmail.com>
License: MIT
Project-URL: Homepage, https://github.com/upraneethkumar/urltrim
Classifier: Programming Language :: Python :: 3
Classifier: License :: OSI Approved :: MIT License
Classifier: Operating System :: OS Independent
Requires-Python: >=3.6
License-File: LICENSE
